{
  "tabPane": [
    {
      "title": "Drive",
      "autoPopulate": true,
      "autoPopulatePrefix": "custom/Drive/",
      "widgetPane": {
        "gridSize": 128.0,
        "showGrid": true,
        "hgap": 8.0,
        "vgap": 8.0,
        "tiles": {
          "0,0": {
            "size": [
              1,
              1
            ],
            "content": {
              "_type": "Boolean Box",
              "_source0": "network_table:///custom/Drive/High Gear",
              "_title": "High Gear",
              "Colors/Color when true": "#7CFC00FF",
              "Colors/Color when false": "#8B0000FF"
            }
          },
          "1,0": {
            "size": [
              1,
              1
            ],
            "content": {
              "_type": "Text View",
              "_source0": "network_table:///custom/Drive/Drive Mode",
              "_title": "Drive Mode"
            }
          },
          "2,0": {
            "size": [
              1,
              1
            ],
            "content": {
              "_type": "Text View",
              "_source0": "network_table:///custom/Drive/Right Encoder",
              "_title": "Right Encoder"
            }
          },
          "3,0": {
            "size": [
              1,
              1
            ],
            "content": {
              "_type": "Text View",
              "_source0": "network_table:///custom/Drive/Right Current",
              "_title": "Right Current"
            }
          },
          "4,0": {
            "size": [
              1,
              1
            ],
            "content": {
              "_type": "Text View",
              "_source0": "network_table:///custom/Drive/Left2 Current",
              "_title": "Left2 Current"
            }
          },
          "5,0": {
            "size": [
              1,
              1
            ],
            "content": {
              "_type": "Text View",
              "_source0": "network_table:///custom/Drive/Yaw",
              "_title": "Yaw"
            }
          },
          "6,0": {
            "size": [
              1,
              1
            ],
            "content": {
              "_type": "Boolean Box",
              "_source0": "network_table:///custom/Drive/Path Done",
              "_title": "Path Done",
              "Colors/Color when true": "#7CFC00FF",
              "Colors/Color when false": "#8B0000FF"
            }
          },
          "7,0": {
            "size": [
              1,
              1
            ],
            "content": {
              "_type": "Boolean Box",
              "_source0": "network_table:///custom/Drive/Brake Mode",
              "_title": "Brake Mode",
              "Colors/Color when true": "#7CFC00FF",
              "Colors/Color when false": "#8B0000FF"
            }
          },
          "0,1": {
            "size": [
              1,
              1
            ],
            "content": {
              "_type": "Text View",
              "_source0": "network_table:///custom/Drive/Left Encoder",
              "_title": "Left Encoder"
            }
          },
          "1,1": {
            "size": [
              1,
              1
            ],
            "content": {
              "_type": "Boolean Box",
              "_source0": "network_table:///custom/Drive/Path Running",
              "_title": "Path Running",
              "Colors/Color when true": "#7CFC00FF",
              "Colors/Color when false": "#8B0000FF"
            }
          },
          "2,1": {
            "size": [
              1,
              1
            ],
            "content": {
              "_type": "Text View",
              "_source0": "network_table:///custom/Drive/Right2 Current",
              "_title": "Right2 Current"
            }
          },
          "3,1": {
            "size": [
              1,
              1
            ],
            "content": {
              "_type": "Text View",
              "_source0": "network_table:///custom/Drive/Left Current",
              "_title": "Left Current"
            }
          },
          "4,1": {
            "size": [
              1,
              1
            ],
            "content": {
              "_type": "Text View",
              "_source0": "network_table:///custom/Drive/Turn",
              "_title": "Turn"
            }
          },
          "5,1": {
            "size": [
              1,
              1
            ],
            "content": {
              "_type": "Text View",
              "_source0": "network_table:///custom/Drive/Heading",
              "_title": "Heading"
            }
          },
          "6,1": {
            "size": [
              1,
              1
            ],
            "content": {
              "_type": "Text View",
              "_source0": "network_table:///custom/Drive/Setpoint",
              "_title": "Setpoint"
            }
          },
          "7,1": {
            "size": [
              1,
              1
            ],
            "content": {
              "_type": "Text View",
              "_source0": "network_table:///custom/Drive/Left Power",
              "_title": "Left Power"
            }
          },
          "0,2": {
            "size": [
              1,
              1
            ],
            "content": {
              "_type": "Text View",
              "_source0": "network_table:///custom/Drive/Right Power",
              "_title": "Right Power"
            }
          }
        }
      }
    }
  ],
  "windowGeometry": {
    "x": -8.0,
    "y": -8.0,
    "width": 1936.0,
    "height": 1066.0
  }
}